featclus/__init__.py
featclus/featclus.py
featclus-0.1.2.dist-info/LICENSE
featclus-0.1.2.dist-info/METADATA
featclus-0.1.2.dist-info/WHEEL
featclus-0.1.2.dist-info/top_level.txt
featclus-0.1.2.dist-info/RECORD
