Metadata-Version: 2.1
Name: featclus
Version: 0.1.2
Summary: This library is built to perform feature selection in clustering models
Home-page: https://github.com/sebassaras02/featclus
Author: Sebastian Sarasti
Author-email: Sebastian Sarasti <sebitas.alejo@hotmail.com>
License: MIT License
Project-URL: Homepage, https://github.com/sebassaras02/featclus
Keywords: Unsupervised Learning,Machine Learning,Clustering
Classifier: License :: OSI Approved :: MIT License
Classifier: Programming Language :: Python
Classifier: Programming Language :: Python :: 3
Requires-Python: >=3.12.4
License-File: LICENSE
Requires-Dist: numpy==2.1.2
Requires-Dist: pandas==2.2.3
Requires-Dist: scikit-learn==1.5.2
Requires-Dist: pytest==8.3.3
Requires-Dist: plotly==5.24.1
Requires-Dist: nbformat==5.10.4
